{
  "title": "Introduction: VP, Global ERP Lead/IT Team",
  "organizer": "Hema Keshava",
  "start": "2026-02-17T12:30:00.0000000",
  "end": "2026-02-17T13:00:00.0000000",
  "location": "Microsoft Teams Meeting",
  "attendees": [
    "Hema Keshava",
    "Didier Blondel",
    "Christophe Hennequin",
    "Jade Nguyen",
    "Michael Markman"
  ],
  "body": "---------- Forwarded message ---------\nFrom: Hema Keshava <Hema.Keshava@abivax.com <mailto:Hema.Keshava@abivax.com> >\nDate: Sun, Feb 15, 2026 at 9:53 PM\nSubject: Introduction: VP, Global ERP Lead/IT Team\nTo: Didier Blondel <Didier.Blondel@abivax.com <mailto:Didier.Blondel@abivax.com> >, Christophe Hennequin <Christophe.Hennequin@abivax.com <mailto:Christophe.Hennequin@abivax.com> >, Jade Nguyen <jade.nguyen-ext@abivax.com <mailto:jade.nguyen-ext@abivax.com> >, Michael Markman <michaelkmarkman@gmail.com <mailto:michaelkmarkman@gmail.com> >\n\nJoin: https://teams.microsoft.com/meet/37247431766948?p=WTvW36a1B8lu62xLok <https://teams.microsoft.com/meet/37247431766948?p=WTvW36a1B8lu62xLok>\n\nPersonal Data Protection Statement: This invitation (including attachments) is intended only for the recipient(s) named above. It may contain confidential or privileged...",
  "rawBody": "---------- Forwarded message ---------\r\nFrom: Hema Keshava <Hema.Keshava@abivax.com <mailto:Hema.Keshava@abivax.com> >\r\nDate: Sun, Feb 15, 2026 at 9:53 PM\r\nSubject: Introduction: VP, Global ERP Lead/IT Team\r\nTo: Didier Blondel <Didier.Blondel@abivax.com <mailto:Didier.Blondel@abivax.com> >, Christophe Hennequin <Christophe.Hennequin@abivax.com <mailto:Christophe.Hennequin@abivax.com> >, Jade Nguyen <jade.nguyen-ext@abivax.com <mailto:jade.nguyen-ext@abivax.com> >, Michael Markman <michaelkmarkman@gmail.com <mailto:michaelkmarkman@gmail.com> >\r\n\r\n\r\n\r\n\r\n \r\n\r\n________________________________________________________________________________\r\n\r\nMicrosoft Teams meeting \r\n\r\nJoin: https://teams.microsoft.com/meet/37247431766948?p=WTvW36a1B8lu62xLok <https://teams.microsoft.com/meet/37247431766948?p=WTvW36a1B8lu62xLok>  \r\n\r\nMeeting ID: 372 474 317 669 48 \r\n\r\nPasscode: qf2Ra2kV \r\n\r\n________________________________\r\n\r\nNeed help? <https://aka.ms/JoinTeamsMeeting?omkt=en-US>  | System reference <https://teams.microsoft.com/l/meetup-join/19%3ameeting_MDEyZDRlYWQtZGU4OC00OGVjLWJlZjItMWZkODVkNDNjM2Jj%40thread.v2/0?context=%7b%22Tid%22%3a%220723fe73-2359-40d2-8c34-7e2aa7415594%22%2c%22Oid%22%3a%2288974f20-cc1f-48f1-bb14-5e0ffc0b7289%22%7d>  \r\n\r\nFor organizers: Meeting options <https://teams.microsoft.com/meetingOptions/?organizerId=88974f20-cc1f-48f1-bb14-5e0ffc0b7289&tenantId=0723fe73-2359-40d2-8c34-7e2aa7415594&threadId=19_meeting_MDEyZDRlYWQtZGU4OC00OGVjLWJlZjItMWZkODVkNDNjM2Jj@thread.v2&messageId=0&language=en-US>  \r\n\r\nPersonal Data Protection Statement: This invitation (including attachments) is intended only for the recipient(s) named above. It may contain confidential or privileged information and should not be read, copied or otherwise used by any other person; for any question on how we process your personal data, or to exercise your rights as per the EU GDPR Regulation (eugdpr.org <http://eugdpr.org> ), please contact us at dpo@abivax.com <mailto:dpo@abivax.com> , or write at PharMarketing, DPO for Abivax, 8 rue Roublot, 94120 Fontenay sous Bois, France. You may also contact your local Data Privacy Authority in your country. Please also note this invitation is using conferencing tool that may record some connection logs (your email address, connection logs and IP address) that will be transferred out of EU in which personal data protection rules are not equivalent to EU GDPR regulation and local privacy laws. By accepting this invitation and joining the conference invitation you do accept those personal data be shared with conferencing tool provider and be transferred outside of EU.\r\n\r\n________________________________________________________________________________",
  "summary": [
    "---------- Forwarded message ---------",
    "From: Hema Keshava <Hema.Keshava@abivax.com <mailto:Hema.Keshava@abivax.com> >"
  ],
  "actions": [],
  "decisions": [],
  "teamsLink": "https://teams.microsoft.com/meet/37247431766948?p=WTvW36a1B8lu62xLok",
  "dialIn": "",
  "generatedAt": "2026-02-17T16:46:18.188Z"
}
